k8s_google_authenticator/__init__.py
k8s_google_authenticator/main.py
k8s_google_authenticator-1.0.2.dist-info/DESCRIPTION.rst
k8s_google_authenticator-1.0.2.dist-info/METADATA
k8s_google_authenticator-1.0.2.dist-info/RECORD
k8s_google_authenticator-1.0.2.dist-info/WHEEL
k8s_google_authenticator-1.0.2.dist-info/entry_points.txt
k8s_google_authenticator-1.0.2.dist-info/metadata.json
k8s_google_authenticator-1.0.2.dist-info/top_level.txt
